{
  "description":
    "Shows NVIDIA GPU stats (utilisation, temperature and memory) in the toolbar. Requires nvidia-settings and nvidia-smi for some features.",
  "shell-version": [
    "3.6",
    "3.8",
    "3.10",
    "3.12",
    "3.14",
    "3.16",
    "3.18",
    "3.20",
    "3.22",
    "3.24"
  ],
  "name": "NVIDIA GPU Stats Tool",
  "settings-schema": "org.gnome.shell.extensions.nvidiautil",
  "uuid": "nvidiautil@ethanwharris",
  "url": "https://github.com/ethanwharris/gnome-nvidia-extension",
  "version": 2
}
